{
    "public": [
    {
        "path": "/",
        "methods": [
            "GET"
        ]
    },
    {
        "path": "/get/api/cibil/upload",
        "methods": [
            "GET"
        ]
    },
    {
        "path": "/get/api/cibil/analysis/",
        "methods": [
            "GET"
        ]
    },
    {
        "path": "/get/api/cibil/clients/grades",
        "methods": [
            "GET"
        ]
    },
    {
        "path": "/get/api/cibil/health",
        "methods": [
            "GET"
        ]
    },
    {
        "path": "/get/check/credit/report/cibil",
        "methods": [
            "GET"
        ]
    },
    {
        "path": "/get/api/cibil/data/calculate",
        "methods": [
            "GET"
        ]
    }]
}